rootutils/__init__.py
rootutils/rootutils.py
tests/__init__.py
tests/conftest.py
tests/test_rootutils.py
rootutils-1.0.7.dist-info/LICENSE
rootutils-1.0.7.dist-info/METADATA
rootutils-1.0.7.dist-info/WHEEL
rootutils-1.0.7.dist-info/top_level.txt
rootutils-1.0.7.dist-info/RECORD
