Metadata-Version: 2.1
Name: rootutils
Version: 1.0.7
Summary: Simple package for easy project root setup
Home-page: https://github.com/ashleve/rootutils
Author: ashleve
Author-email: ashlevegalaxy@gmail.com
License: MIT
Requires-Python: >=3.7.0
License-File: LICENSE
